gxsmread/__init__.py
gxsmread/channel_config.py
gxsmread/filename.py
gxsmread/preprocess.py
gxsmread/read.py
gxsmread/spec.py
gxsmread/utils.py
gxsmread-0.2.4.dist-info/LICENSE
gxsmread-0.2.4.dist-info/METADATA
gxsmread-0.2.4.dist-info/WHEEL
gxsmread-0.2.4.dist-info/RECORD
