Metadata-Version: 2.3
Name: gxsmread
Version: 0.2.4
Summary: Read gxsm data files
License: GPL-2.0-only
Author: Nick Sullivan
Author-email: nsulmol@gmail.com
Maintainer: Nick Sullivan
Maintainer-email: nsulmol@gmail.com
Requires-Python: >=3.11
Classifier: Development Status :: 3 - Alpha
Classifier: Intended Audience :: Developers
Classifier: Topic :: Scientific/Engineering :: Information Analysis
Classifier: Programming Language :: Python :: 3
Classifier: License :: OSI Approved :: GNU General Public License v2 (GPLv2)
Classifier: Operating System :: OS Independent
Provides-Extra: dev
Provides-Extra: io
Provides-Extra: parallel
Requires-Dist: dask (>=2025.5.1,<2026.0.0)
Requires-Dist: debugpy (>=1.6.7,<2.0.0) ; extra == "dev"
Requires-Dist: netcdf4 (>=1.7.2,<2.0.0)
Requires-Dist: pandas (>=2.3.0,<3.0.0)
Requires-Dist: pytest (>=7.4.0,<8.0.0) ; extra == "dev"
Requires-Dist: tomli (>=2.0.1,<3.0.0)
Requires-Dist: xarray (>=2025.4.0,<2026.0.0)
Requires-Dist: xarray[io] (>=2025.4.0,<2026.0.0) ; extra == "io"
Requires-Dist: xarray[parallel] (>=2025.4.0,<2026.0.0) ; extra == "parallel"
Project-URL: Homepage, https://github.com/grutter-spm-group/gxsmread
Project-URL: Repository, https://github.com/grutter-spm-group/gxsmread.git
